[
  {
    "resume_id": "CVs\\batch_2\\10646_TAMAGHNO_BARDHAN.txt",
    "resume_text": "\n\n\n\n\n\n\n\nTAMAGHNO BARDHAN\nAddress:  29/2, Ananda Mohan Basu Road, Babupara,  P.O-Siliguri Town, Dist- Darjeeling\nPin-734004\nContact no: 9563326562\nE-Mail:  bardhantamaghno@gmail.com\n\n                \u2026\u2026\u2026\u2026\u2026\u2026\u2026\u2026\u2026\u2026\u2026\u2026\u2026\u2026\u2026 OVERVIEW \u2026\u2026\u2026\u2026\u2026\u2026\u2026\u2026\u2026\u2026\u2026\u2026\u2026.\u2026.....  \nSenior Process Executive-Data with 1 Year  8months Experience in Quality Analysis. Service delivery in an International Business 2 Client environment.\n\n            \n          \u2026\u2026\u2026\u2026\u2026\u2026\u2026\u2026\u2026\u2026\u2026\u2026\u2026\u2026\u2026 CARRER OBJECTIVE \u2026\u2026\u2026\u2026\u2026\u2026\u2026\u2026\u2026\u2026\u2026\u2026\u2026.\u2026.....  \n  Seeking a position in your organization where I can show my  abilities, skills and academic knowledge and find an opportunity for a sound growth and all round development.\n\n               \u2026\u2026\u2026\u2026\u2026\u2026\u2026\u2026\u2026\u2026\u2026\u2026\u2026\u2026\u2026..  Personal Information \u2026\u2026\u2026\u2026\u2026\u2026\u2026\u2026\u2026\u2026\u2026\u2026\u2026                          \nDate of Birth: 10-06-1992\nFather\u2019s Name: Tanmay Kanti Bardhan\n                  \u2026\u2026\u2026\u2026\u2026\u2026\u2026\u2026\u2026\u2026\u2026\u2026\u2026\u2026\u2026\u2026...   Academics   \u2026\u2026\u2026\u2026\u2026\u2026\u2026\u2026\u2026\u2026\u2026\u2026\u2026\u2026\u2026\u2026..\n\tDEGREE\n\tCOLLEGE/UNIVERSITY\n\tYEAR OF PASSING\n\n\tMadyamik\n\tW.B.B.S.E\n\t2008\n\n\tHigher Secondary\n\tW.B.C.H.S.E\n\t2010\n\n\tGraduation\n\tCALCUTTA UNIVERSITY\n\t2013\n\n\tPost Graduate In Software Engg\n\tNIIT\n\t2016\n\n\n\n                 \u2026\u2026\u2026\u2026\u2026\u2026\u2026\u2026\u2026\u2026\u2026\u2026\u2026\u2026\u2026\u2026...   Strength   \u2026\u2026\u2026\u2026\u2026\u2026\u2026\u2026\u2026\u2026\u2026\u2026\u2026\u2026\u2026\u2026..\n\n\u00b7 I am Gental Natured.\n\u00b7 Quick Learner.\n\u00b7 I believe in Hard Work\n         \u2026\u2026\u2026\u2026\u2026\u2026\u2026\u2026\u2026\u2026\u2026\u2026\u2026\u2026\u2026\u2026...   Work Experience   \u2026\u2026\u2026\u2026\u2026\u2026\u2026\u2026\u2026\u2026\u2026\u2026\u2026\u2026\u2026\u2026..\n\n       Working in Cognizant Technology Solutions from August 2016 to April 2018 as a Senior Process Executive Data in Quality Team as a Quality Analyst. \n\n\n\u2026\u2026\u2026\u2026\u2026\u2026\u2026\u2026\u2026\u2026\u2026\u2026\u2026\u2026\u2026\u2026\u2026\u2026\u2026..TechnicalSkill \u2026\u2026\u2026\u2026\u2026\u2026\u2026\u2026\u2026\u2026\u2026\u2026.\u2026\u2026\u2026\u2026\u2026\u2026\u2026.\n\n\u00b7 Operating Systems:       MS Windows XP, 7, 8, 10\n\u00b7 MS Office                :       MS word, MS PowerPoint, MS Excel.\n\u00b7 Computer Application.\n \n\n              \u2026\u2026\u2026\u2026\u2026\u2026\u2026\u2026\u2026\u2026\u2026\u2026\u2026\u2026\u2026\u2026\u2026\u2026.. Personal Skills \u2026\u2026\u2026\u2026\u2026\u2026\u2026\u2026\u2026\u2026\u2026\u2026\u2026\u2026\u2026\u2026\u2026\u2026\u2026..\n\u00b7 Target Oriented, Self Motivated and open to flexible nature of work.\n\u00b7 Comprehensive problem solving abilities.\n\u00b7 Good Communication skills.\n\n                \n                   \u2026\u2026\u2026\u2026\u2026\u2026\u2026\u2026\u2026\u2026\u2026\u2026\u2026\u2026\u2026\u2026\u2026.. Languages Known \u2026\u2026\u2026\u2026\u2026\u2026\u2026\u2026\u2026\u2026\u2026\u2026\u2026\u2026\u2026\u2026\u2026..\n               English, Bengali and Hindi.\n\n                 \u2026\u2026\u2026\u2026\u2026\u2026\u2026\u2026\u2026\u2026\u2026\u2026\u2026\u2026..... Area of Interest \u2026\u2026\u2026\u2026\u2026\u2026\u2026\u2026\u2026\u2026\u2026\u2026\u2026\u2026\u2026\u2026\u2026\u2026\u2026..\n                                Travelling, Reading Books, Climbing Mountains\n\n                  \u2026\u2026\u2026\u2026\u2026\u2026\u2026\u2026\u2026\u2026\u2026\u2026\u2026\u2026\u2026\u2026\u2026\u2026\u2026.. Declaration \u2026\u2026\u2026\u2026\u2026\u2026\u2026\u2026\u2026\u2026\u2026\u2026\u2026\u2026\u2026\u2026\u2026\u2026\u2026..\n            I hereby declare that the above information furnished is correct to the best of my knowledge.\n\n          Place:                          Kolkata.                                                                                         \n          Date:                                                                                                         (Tamaghno Bardhan)\n",
    "extracted_info": {
      "education": [
        {
          "degree": "Software Engineering",
          "institution": "NIIT",
          "graduation_date": "2016"
        }
      ],
      "work_experience": [
        {
          "company": "Cognizant Technology Solutions",
          "title": "Senior Process Executive-Data",
          "start_date": "August 2016",
          "end_date": "April 2018",
          "duration": 1.5,
          "responsibilities": [],
          "technical_skills": [
            "MS Office",
            "MS Excel",
            "MS PowerPoint",
            "MS Word",
            "Windows XP, 7, 8, 10"
          ],
          "soft_skills": [
            "Target Oriented",
            "Self Motivated",
            "Open to Flexible Nature of Work",
            "Comprehensive Problem Solving Abilities",
            "Good Communication Skills"
          ]
        }
      ],
      "extra_skills": {
        "Technical skills": ["English, Bengali and Hindi"],
        "Soft skills": []
      }
    }
  },
  {
    "resume_id": "CVs\\batch_11\\4103_RANJITHAR.txt",
    "resume_text": "\n\n\n\n\n\n\n\n\n\n\n\n\n\n\n\n\n\n\n\n\n\n\n\nRANJITHAR Phone:+919659512536\nE-mail:ranjitharadhakrishnan1995@gmail.com\n\nProfessionalSummary:\n\n\uf06c Having2YrsofITExperienceinOraclePL/SQLDeveloper.\n\uf06c Experienceincludesapplicationdevelopmentontelecommunicationsectorbasedonsql/plsql.\n\uf06c Involvedinthecontinuousenhancementsandfixingofproductionproblems.\n\uf06c DevelopedPL/SQLtriggerstoupdate,insertontemporarytableforback-upandhistorypurpose.\n\uf06c CreatedPL/SQLstoredprocedures,functionsandpackagesforretrievingormaintainingdatain\n\napplication.\n\uf06c Createdscriptstocreatenew tables,views,queriesfornew enhancementintheapplicationusing\n\nPLSQLDeveloper.\n\uf06c Createdindexesonthetablesforfasterretrievalofthedatatoenhancedatabaseperformance.\n\uf06c Creationofdatabaseobjectsliketables,views,materializedviews,proceduresandpackagesusing\n\noracletoolslikePL/SQLDeveloperandSQL*plus.\n\uf06c CreatedGlobalTemporaryTablesandExternaltablesforstoringlargedata.\n\uf06c ExtensivelyusedtheadvancedfeaturesofPL/SQLlikeRecords,Tables,ObjecttypesandDynamic\n\nSQL.\n\uf06c HandlederrorsusingExceptionHandlingextensivelyfortheeaseofdebugginganddisplayingthe\n\nerrormessagesintheapplication.\n\uf06c ExpertiseinSQLandPL/SQLdatabaseprogramming.\n\uf06c HavingbasicknowledgeaboutUnixshellscripting.\n\uf06c Havinghandsonexperienceinjavascripts,html,corejava\n\uf06c Havingknowledgeinexceptionhandling,multithreadingandcollectionsinjava.\n\uf06c ACommittedteam playerwithorganizationalandinterpersonalskills.\n\nTechnicalSkillSets:\nOperatingSystem Windows7/8,WindowsXP\nDatabase Oracle10g,Oracle11g,MySql\nLanguages SQL,PL/SQL,J2E,JSE,html\nOthers SQL*Plus,PL/SQLDEVELOPER,eclipse\nApplicationHandled MagNetIPD\n\nWorkExperienceDetails(2years):\n\nEmployer. TechMahindraPrivateLimitedasSoftwareEngineerfrom 29-Sep-2016totillnow.\n\nProjectName MmO2-Telefonica-UK-MagnetDevelopment\n\nClient Telefonica\u2013UK\nTechnology Oracle11g,SQL/PLSQL,UNI\nProjectDuration 29-Sep-2016toTillnow.\nRole ApplicationDeveloper(SoftwareEngineer)\nApplicationhandled MagNetIPD\n\nProjectDescription:\nMaintaininganddevelopingtheapplicationsfortheclientTelefonica(UK)forretrievingthe\ntelecom datafrom variousinterfacesliketransmissionplanning&Radioplanninggroupsand\nmaintainingthedatabase.\n\n\n\nApplicationHandled:MagNetIPD\nMagnetIPDisoneoftheprimaryStructuredplanninganddatabuildtoolusedinTelecom toprovide\nFilesthatshowsplannedchangestothelivenetwork.Itprovidesbasedataandhistoricaldataon\ncells/sitesdetail,parameterdetails.\nItisacentralizeddatabasethatRadio/transmissionplannerscanusewhencreatingvarioustypesof\n\nplans\n2G/3G/4G.\n\nKeyResponsibilities:\n1. Creationofdatabaseobjectsliketables,views,materializedviews,proceduresandpackagesbased\n\nonSoR.\n2. WorkonAgileMethodology.\n3. WorkonmodifyingexistingOracleobjectstofixingofproductionproblems.\n4. InvolvedinperformancetuningofPL/SQLandSQLcodes.\n5. PerformingUnittestingafterdevelopmenthasdoneaccordingtotherequirement.\n6. PerformingSanitychecksofallOracleobjectsonLiveNetworkaftereveryreleases.\n7. Maintainingdetaileddocumentationaboutthedevelopmentwork(listoforacleobjectsmodified&\n\nnewlycreated)hasdoneundereveryrequirementraised.\n\nCertification&Training:\n\uf0d8 ELITE(EntryLevelIntegratedTrainingandEnablement)\u20136monthstrainingProgram ofTech\n\nMahindra.\n\uf0d8 Attendedwebinars&traininginSQL/PLSQL.\n\nQualifications:\n\uf0d8 B.E(ECE)from AnnaUniversity,SriEshwarCollegeofEngineeringCoimbatore.(85.2%).\n\uf0d8 12\n\nth\nMariammalgirlsHscSchool,Pollachi(94.2%)\n\n\uf0d8 10\nth\n\nTmt.RuckmaniammalHscSchool,Pollachi(97%).\n\nPersonalDetails:\nFather\u2019sName : Mr.RadhakrishnanK\nDOB : 18-MAR-1995\nGender : Female\nMaritalStatus : Single\nPassportNo : N5249298\nLinguisticSkills : English,Tamil\n\nPlace: (RanjithaR)\nDate:\n\n\n",
    "extracted_info": {
      "education": [
        {
          "degree": "B.E(ECE)",
          "institution": "Anna University",
          "graduation_date": "N\/A"
        }
      ],
      "work_experience": [
        {
          "company": "Tech Mahindra Private Limited",
          "title": "Software Engineer",
          "start_date": "September 2016",
          "end_date": "Present",
          "duration": 8.5,
          "responsibilities": [
            "Creation of database objects like tables, views, materialized views, procedures and packages using oracle tools like PL/SQL Developer and SQL*Plus.",
            "Creation of Global Temporary Tables and External Tables for storing large data.",
            "Extensively used the advanced features of PL/SQL like Records, Tables, Object types and Dynamic SQL.",
            "Handling errors using Exception Handling extensively for the ease of debugging and displaying the error messages in the application."
          ],
          "technical_skills": [
            "Windows 7/8",
            "Windows XP",
            "Oracle 10g",
            "Oracle 11g",
            "MySql",
            "SQL",
            "PL/SQL",
            "J2E",
            "JSE",
            "html",
            "eclipse",
            "SQL*Plus",
            "Unix shell scripting",
            "Javascripts", 
            "Corejava",
            "PL/SQL Developer"
          ],
          "soft_skills": [
            "Committed Team Player",
            "Organizational and Interpersonal Skills"
          ]
        }
      ],
      "extra_skills": {
        "Technical skills": [],
        "Soft skills": []
      }
    }
  },
  {
    "resume_id": "CVs\\batch_11\\14772_PRIYOTAM_BOSE.txt",
    "resume_text": "\n\n\n\n\n\n\n\n\n\n\n\n\n\n\n\n\n\n\n\n\n\n\n\n\n\n\n\n\n\n\n\n\n\n\n\n\n\nPRIYOTAM BOSE\n\nE-mail Id:  priyotambose05@gmail.com                                                           Contact number: +919851333183\n\nCareer Objective:  For challenging opportunities in the organization which can refine the skills and expand my knowledge. Utilize all my skills for the growth of the organization.\n\n\u2026\u2026\u2026\u2026\u2026\u2026\u2026\u2026\u2026\u2026\u2026\u2026\u2026\u2026\u2026\u2026\u2026\u2026\u2026\u2026\u2026\u2026\u2026\u2026\u2026\u2026\u2026\u2026\u2026\u2026\u2026\u2026\u2026\u2026\u2026\u2026\u2026\u2026\u2026\u2026\u2026\u2026\u2026\u2026\u2026\u2026\u2026\u2026\u2026\u2026\u2026\u2026\u2026\u2026\u2026\u2026\u2026\u2026\u2026\u2026\u2026\n\nSkill Set:\n\n\u00b7 Excellent problems solving and analytical skills.\n\u00b7 Organizing and planning skills.\n\n\u00b7 Excellent communication and writing skills.\n\n\u00b7 Excellent ability to plan, organize and follow through.\n\n\u00b7 Able to visualize a situation.\n\n\u00b7 Responsible for other duties as assigned.\nComputer Skill: \n\n            Computer knowledge in MS office, MS excel, MS PowerPoint.\n\u2026\u2026\u2026\u2026\u2026\u2026\u2026\u2026\u2026\u2026\u2026\u2026\u2026\u2026\u2026\u2026\u2026\u2026\u2026\u2026\u2026\u2026\u2026\u2026\u2026\u2026\u2026\u2026\u2026\u2026\u2026\u2026\u2026\u2026\u2026\u2026\u2026\u2026\u2026\u2026\u2026\u2026\u2026\u2026\u2026\u2026\u2026\u2026\u2026\u2026\u2026\u2026\u2026\u2026\u2026\u2026\u2026\u2026\u2026\u2026\u2026\n\nEducational Qualification:\n\n\tSl\n\nNO.\n\tBOARD \\ UNIVERSITY\n\tNAME OF EXAMINATION\n\tYEAR OF\n\nPASSING\n\tPercentage\n\n\t1.\n\tW.B.B.S.E.\n\tMadhyamik\n\t2006\n\t63\n\n\t2.\n\tW.B.B.H.S.E.\n\tHigher Secondary\n\t2008\n\t69.2\n\n\t3.\n\tCALCUTTA UNIVERSITY\n\tBachelor of Commerce\n\t2011\n\t42.16\n\n\nPersonal Information:\n\nFather\u2019s Name:                                        Nemai Chand Bose\n\nMother\u2019s Name:                                      Patrali Bose\n\nDate of Birth:                                           19th April 1990\n\nNationality:                                              Indian\n\nSex:                                                            Male\n\nBlood Group:                                           O+\n\nSchool:                                                      Saltore Colliery High School\n\nHigher Secondary:                                  Shantinagar Vidyamandir\n\nCollege (Graduation):                            Prafulla Chandra College\n\nMother Tongue:                                     Bengali\n\nLanguage Known:                                  English, Hindi, Bengali.\n\nMartial Status:                                       Single\n\nCaste:                                                       General\n\nHobby:                                                     Collection of political news       \n\u2026\u2026\u2026\u2026\u2026\u2026\u2026\u2026\u2026\u2026\u2026\u2026\u2026\u2026\u2026\u2026\u2026\u2026\u2026\u2026\u2026\u2026\u2026\u2026\u2026\u2026\u2026\u2026\u2026\u2026\u2026\u2026\u2026\u2026\u2026\u2026\u2026\u2026\u2026\u2026\u2026\u2026\u2026\u2026\u2026\u2026\u2026\u2026\u2026\u2026\u2026\u2026\u2026\u2026\u2026..\n Permanent Address: \n\nPriyotam Bose \n\n                                                             Radhanagar Road\n\n                                                             PO-Burnpur\n\n                                                             PS-Hirapur\n\n                                                             Dist-Burdwan\n\n                                                             Pin-713325      \n\n\nPresent Address:\n\n\nPriyotam Bose\n\n\n\n\n\n\n\n30/3, Mahabir Enclave\n\nBlock C Top floor\n\nHedarhat Mukundpur, Near Jora Bridge, Santoshpur\n\nKolkata-700 099\n\n\n\n\n\n\n\n\n\n\n\n\n\n\n\n\n                                                                                                                      \nDate: -             3/5/2012                                                                                                       Candidate Signature\n",
    "extracted_info": {
      "education": [
        {
          "degree": "Bachelor of Commerce",
          "institution": "Calcutta University",
          "graduation_date": "2011"
        }
      ],
      "work_experience": [],
      "extra_skills": {
        "Technical skills": [
          "MS Office", 
          "MS Excel", 
          "MS PowerPoint", 
          "English", 
          "Bengali", 
          "Hindi"
        ],
        "Soft skills": [
          "Problem solver",
          "Organizing and planning skills",
          "Excellent communication and writing skills",
          "Excellent ability to plan, organize and follow through",
          "Able to visualize a situation"
        ]
      }
    }
  },
  {
    "resume_id": "CVs\\batch_11\\9878_PRIYOTAM_BOSE (2).txt",
    "resume_text": "\n\n\n\n\n\n\n\n\n\n\n\n\n\n\n\n\n\n\n\n\n\n\n\n\n\n\n\n\n\n\n\n\n\n\n\n\n\nPRIYOTAM BOSE\n\nE-mail Id:  priyotambose05@gmail.com                                                           Contact number: +919851333183\n\nCareer Objective:  For challenging opportunities in the organization which can refine the skills and expand my knowledge. Utilize all my skills for the growth of the organization.\n\n\u2026\u2026\u2026\u2026\u2026\u2026\u2026\u2026\u2026\u2026\u2026\u2026\u2026\u2026\u2026\u2026\u2026\u2026\u2026\u2026\u2026\u2026\u2026\u2026\u2026\u2026\u2026\u2026\u2026\u2026\u2026\u2026\u2026\u2026\u2026\u2026\u2026\u2026\u2026\u2026\u2026\u2026\u2026\u2026\u2026\u2026\u2026\u2026\u2026\u2026\u2026\u2026\u2026\u2026\u2026\u2026\u2026\u2026\u2026\u2026\u2026\n\nSkill Set:\n\n\u00b7 Excellent problems solving and analytical skills.\n\u00b7 Organizing and planning skills.\n\n\u00b7 Excellent communication and writing skills.\n\n\u00b7 Excellent ability to plan, organize and follow through.\n\n\u00b7 Able to visualize a situation.\n\n\u00b7 Responsible for other duties as assigned.\nComputer Skill: \n\n            Computer knowledge in MS office, MS excel, MS PowerPoint.\n\u2026\u2026\u2026\u2026\u2026\u2026\u2026\u2026\u2026\u2026\u2026\u2026\u2026\u2026\u2026\u2026\u2026\u2026\u2026\u2026\u2026\u2026\u2026\u2026\u2026\u2026\u2026\u2026\u2026\u2026\u2026\u2026\u2026\u2026\u2026\u2026\u2026\u2026\u2026\u2026\u2026\u2026\u2026\u2026\u2026\u2026\u2026\u2026\u2026\u2026\u2026\u2026\u2026\u2026\u2026\u2026\u2026\u2026\u2026\u2026\u2026\n\nEducational Qualification:\n\n\tSl\n\nNO.\n\tBOARD \\ UNIVERSITY\n\tNAME OF EXAMINATION\n\tYEAR OF\n\nPASSING\n\tPercentage\n\n\t1.\n\tW.B.B.S.E.\n\tMadhyamik\n\t2006\n\t63\n\n\t2.\n\tW.B.B.H.S.E.\n\tHigher Secondary\n\t2008\n\t69.2\n\n\t3.\n\tCALCUTTA UNIVERSITY\n\tBachelor of Commerce\n\t2011\n\t42.16\n\n\nPersonal Information:\n\nFather\u2019s Name:                                        Nemai Chand Bose\n\nMother\u2019s Name:                                      Patrali Bose\n\nDate of Birth:                                           19th April 1990\n\nNationality:                                              Indian\n\nSex:                                                            Male\n\nBlood Group:                                           O+\n\nSchool:                                                      Saltore Colliery High School\n\nHigher Secondary:                                  Shantinagar Vidyamandir\n\nCollege (Graduation):                            Prafulla Chandra College\n\nMother Tongue:                                     Bengali\n\nLanguage Known:                                  English, Hindi, Bengali.\n\nMartial Status:                                       Single\n\nCaste:                                                       General\n\nHobby:                                                     Collection of political news       \n\u2026\u2026\u2026\u2026\u2026\u2026\u2026\u2026\u2026\u2026\u2026\u2026\u2026\u2026\u2026\u2026\u2026\u2026\u2026\u2026\u2026\u2026\u2026\u2026\u2026\u2026\u2026\u2026\u2026\u2026\u2026\u2026\u2026\u2026\u2026\u2026\u2026\u2026\u2026\u2026\u2026\u2026\u2026\u2026\u2026\u2026\u2026\u2026\u2026\u2026\u2026\u2026\u2026\u2026\u2026..\n Permanent Address: \n\nPriyotam Bose \n\n                                                             Radhanagar Road\n\n                                                             PO-Burnpur\n\n                                                             PS-Hirapur\n\n                                                             Dist-Burdwan\n\n                                                             Pin-713325      \n\n\nPresent Address:\n\n\nPriyotam Bose\n\n\n\n\n\n\n\n30/3, Mahabir Enclave\n\nBlock C Top floor\n\nHedarhat Mukundpur, Near Jora Bridge, Santoshpur\n\nKolkata-700 099\n\n\n\n\n\n\n\n\n\n\n\n\n\n\n\n\n                                                                                                                      \nDate: -             3/5/2012                                                                                                       Candidate Signature\n",
    "extracted_info": {
      "education": [
        {
          "degree": "Bachelor of Commerce",
          "institution": "Calcutta University",
          "graduation_date": "2011"
        }
      ],
      "work_experience": [],
      "extra_skills": {
        "Technical skills": [
          "MS Office", 
          "MS Excel", 
          "MS PowerPoint", 
          "English", 
          "Bengali", 
          "Hindi"
        ],
        "Soft skills": [
          "Problem solver",
          "Organizing and planning skills",
          "Excellent communication and writing skills",
          "Excellent ability to plan, organize and follow through",
          "Able to visualize a situation"
        ]
      }
    }
  },
  {
    "resume_id": "CVs\\batch_14\\6221_PRIYOTAM_BOSE (1).txt",
    "resume_text": "\n\n\n\n\n\n\n\n\n\n\n\n\n\n\n\n\n\n\n\n\n\n\n\n\n\n\n\n\n\n\n\n\n\n\n\n\n\nPRIYOTAM BOSE\n\nE-mail Id:  priyotambose05@gmail.com                                                           Contact number: +919851333183\n\nCareer Objective:  For challenging opportunities in the organization which can refine the skills and expand my knowledge. Utilize all my skills for the growth of the organization.\n\n\u2026\u2026\u2026\u2026\u2026\u2026\u2026\u2026\u2026\u2026\u2026\u2026\u2026\u2026\u2026\u2026\u2026\u2026\u2026\u2026\u2026\u2026\u2026\u2026\u2026\u2026\u2026\u2026\u2026\u2026\u2026\u2026\u2026\u2026\u2026\u2026\u2026\u2026\u2026\u2026\u2026\u2026\u2026\u2026\u2026\u2026\u2026\u2026\u2026\u2026\u2026\u2026\u2026\u2026\u2026\u2026\u2026\u2026\u2026\u2026\u2026\n\nSkill Set:\n\n\u00b7 Excellent problems solving and analytical skills.\n\u00b7 Organizing and planning skills.\n\n\u00b7 Excellent communication and writing skills.\n\n\u00b7 Excellent ability to plan, organize and follow through.\n\n\u00b7 Able to visualize a situation.\n\n\u00b7 Responsible for other duties as assigned.\nComputer Skill: \n\n            Computer knowledge in MS office, MS excel, MS PowerPoint.\n\u2026\u2026\u2026\u2026\u2026\u2026\u2026\u2026\u2026\u2026\u2026\u2026\u2026\u2026\u2026\u2026\u2026\u2026\u2026\u2026\u2026\u2026\u2026\u2026\u2026\u2026\u2026\u2026\u2026\u2026\u2026\u2026\u2026\u2026\u2026\u2026\u2026\u2026\u2026\u2026\u2026\u2026\u2026\u2026\u2026\u2026\u2026\u2026\u2026\u2026\u2026\u2026\u2026\u2026\u2026\u2026\u2026\u2026\u2026\u2026\u2026\n\nEducational Qualification:\n\n\tSl\n\nNO.\n\tBOARD \\ UNIVERSITY\n\tNAME OF EXAMINATION\n\tYEAR OF\n\nPASSING\n\tPercentage\n\n\t1.\n\tW.B.B.S.E.\n\tMadhyamik\n\t2006\n\t63\n\n\t2.\n\tW.B.B.H.S.E.\n\tHigher Secondary\n\t2008\n\t69.2\n\n\t3.\n\tCALCUTTA UNIVERSITY\n\tBachelor of Commerce\n\t2011\n\t42.16\n\n\nPersonal Information:\n\nFather\u2019s Name:                                        Nemai Chand Bose\n\nMother\u2019s Name:                                      Patrali Bose\n\nDate of Birth:                                           19th April 1990\n\nNationality:                                              Indian\n\nSex:                                                            Male\n\nBlood Group:                                           O+\n\nSchool:                                                      Saltore Colliery High School\n\nHigher Secondary:                                  Shantinagar Vidyamandir\n\nCollege (Graduation):                            Prafulla Chandra College\n\nMother Tongue:                                     Bengali\n\nLanguage Known:                                  English, Hindi, Bengali.\n\nMartial Status:                                       Single\n\nCaste:                                                       General\n\nHobby:                                                     Collection of political news       \n\u2026\u2026\u2026\u2026\u2026\u2026\u2026\u2026\u2026\u2026\u2026\u2026\u2026\u2026\u2026\u2026\u2026\u2026\u2026\u2026\u2026\u2026\u2026\u2026\u2026\u2026\u2026\u2026\u2026\u2026\u2026\u2026\u2026\u2026\u2026\u2026\u2026\u2026\u2026\u2026\u2026\u2026\u2026\u2026\u2026\u2026\u2026\u2026\u2026\u2026\u2026\u2026\u2026\u2026\u2026..\n Permanent Address: \n\nPriyotam Bose \n\n                                                             Radhanagar Road\n\n                                                             PO-Burnpur\n\n                                                             PS-Hirapur\n\n                                                             Dist-Burdwan\n\n                                                             Pin-713325      \n\n\nPresent Address:\n\n\nPriyotam Bose\n\n\n\n\n\n\n\n30/3, Mahabir Enclave\n\nBlock C Top floor\n\nHedarhat Mukundpur, Near Jora Bridge, Santoshpur\n\nKolkata-700 099\n\n\n\n\n\n\n\n\n\n\n\n\n\n\n\n\n                                                                                                                      \nDate: -             3/5/2012                                                                                                       Candidate Signature\n",
    "extracted_info": {
      "education": [
        {
          "degree": "Bachelor of Commerce",
          "institution": "Calcutta University",
          "graduation_date": "2011"
        }
      ],
      "work_experience": [],
      "extra_skills": {
        "Technical skills": [
          "MS Office", 
          "MS Excel", 
          "MS PowerPoint", 
          "English", 
          "Bengali", 
          "Hindi"
        ],
        "Soft skills": [
          "Problem solver",
          "Organizing and planning skills",
          "Excellent communication and writing skills",
          "Excellent ability to plan, organize and follow through",
          "Able to visualize a situation"
        ]
      }
    }
  }
]